st_input/__init__.py
st_input/frontend/index.html
st_input/frontend/main.js
st_input/frontend/streamlit-component-lib.js
st_input/frontend/style.css
streamlit_input-0.1.2.dist-info/LICENSE
streamlit_input-0.1.2.dist-info/METADATA
streamlit_input-0.1.2.dist-info/WHEEL
streamlit_input-0.1.2.dist-info/top_level.txt
streamlit_input-0.1.2.dist-info/RECORD
