Metadata-Version: 2.1
Name: streamlit-input
Version: 0.1.2
Summary: This a general streamlit input widget, that supports additional input types.
Author: akbor
Author-email: noemail@example.com
Requires-Python: >=3.7
License-File: LICENSE
Requires-Dist: streamlit >=1.2
Requires-Dist: jinja2
